{
  "annotations": [
    {
      "start_time": 437,
      "end_time": 444,
      "annotation": [
        {
          "type": "paragraph",
          "children": [
            {
              "text": "This clip documents fear of crime in Tucson, Arizona. Notably, Tucson is not an example of the “fading industrial center” discussed in much of this set; instead, it was a growing city in the “Sun Belt,” a region in the southern portion of the United States that didn’t suffer the same economic problems as the “Rust Belt” in the Northeast. While the population of many cities stagnated or shrunk in this era, Tucson was exploding: between 1950 and 1980, the city’s population grew from 45,000 to over 330,000, an over 600% increase. This shows that the rise of crime was not simply a mechanical result of economic dislocation associated with deindustrialization; the crime wave of the 1970s and 1980s had myriad causes. It also shows that social problems intensified in urban centers across the country, even in cities that were not facing significant economic hardship.\n\n"
            }
          ]
        }
      ],
      "tags": [
        {
          "category": "Context",
          "tag": "Historical Background"
        }
      ],
      "uuid": "6dfc30d0-5c54-4592-bb89-4d97c70d1f81"
    },
    {
      "start_time": 444,
      "end_time": 507,
      "annotation": [
        {
          "type": "paragraph",
          "children": [
            {
              "text": "The enhanced home security efforts depicted in this segment provide just one example of how communities sought to protect themselves from rising crime. For example, in 1972, the National Sheriffs Association founded the National Neighborhood Watch program, and communities across the country formed local organizations devoted to staying vigilant about the threat of crime and coordinating with local law enforcement\n\n"
            }
          ]
        }
      ],
      "tags": [
        {
          "category": "Context",
          "tag": "Deeper Explanation"
        }
      ],
      "uuid": "7693d21f-aa15-40bd-b5bf-70c91f554994"
    },
    {
      "start_time": 582,
      "end_time": 608,
      "annotation": [
        {
          "type": "paragraph",
          "children": [
            {
              "text": "This minister describes how individual churchgoing were withdrawing from social service efforts based around generosity, as the rise in crime had created an “us” versus “them” mentality that distanced parishioners from poor people in the city. This trend parallels a broader national trend identified by historians like Julilly Kohler-Hausman, who argues in her book Getting Tough: Welfare and Imprisonment in 1970s America, that the rise of a “tough on crime” politics coincided with the rise of welfare retrenchment policies. At a local, state, and national level, she argues that there was a shift away from social service programs and towards more intensive policing and incarceration.\n\n"
            }
          ]
        }
      ],
      "tags": [
        {
          "category": "Context",
          "tag": "Deeper Explanation"
        }
      ],
      "uuid": "2d7997d9-02ff-433c-acd3-06ce96d35215"
    }
  ],
  "set": "Default",
  "event_id": "f89c3aa3-1ab8-43ea-a3e3-0efd48ba8c65",
  "source_id": "e1d56494-abeb-4d5f-9ba1-1456d6b3734e"
}