{
  "audiovisual_files": {
    "b79a0c08-5ed5-4101-a548-1a16d99c091f": {
      "label": "AV File 1",
      "file_url": "https://americanarchive.org/media/cpb-aacip-879905812d0/download",
      "duration": 3451,
      "file_type": "Video"
    }
  },
  "auto_generate_web_page": false,
  "description": [
    {
      "type": "paragraph",
      "children": [
        {
          "text": ""
        }
      ]
    }
  ],
  "created_at": "2026-06-02T03:09:35.120Z",
  "created_by": "benleff84",
  "label": "Urban Decay in the South Bronx",
  "updated_at": "2026-06-02T03:10:10.347Z",
  "updated_by": "benleff84",
  "rights_statement": "",
  "av_file_order": [
    "b79a0c08-5ed5-4101-a548-1a16d99c091f"
  ]
}