{
  "content": [
    {
      "type": "paragraph",
      "children": [
        {
          "text": ""
        }
      ]
    },
    {
      "type": "paragraph",
      "children": [
        {
          "text": "In the mid-twentieth century, cities across the country built giant public housing projects to house low-income residents. The goal was to replace deteriorating slums that had traditionally housed the urban poor. Notably, suburbs were largely successful in fighting efforts to build public housing outside of inner cities, and by the 1960s and 1970s, complexes were typically heavily racially segregated. Additionally, gathering the poor in high-rise apartments concentrated the problems associated with extreme poverty in one densely packed location. The problems of entrenched poverty only got worse with deindustrialization and the collapse of urban economies. As a result, housing projects became riddled with gang activity, drug dealing, and violence, and were deployed as symbols of the failure of government anti-poverty efforts. The problems in Boston’s Columbia Point Housing Project were explored in this 1978 episode of "
        },
        {
          "text": "The MacNeil Lehrer Report",
          "italic": true
        },
        {
          "text": " entitled “What to Do with the Failures in Public Housing: Fix Them Up, or Tear 'Em Down?\""
        }
      ]
    },
    {
      "type": "paragraph",
      "children": [
        {
          "text": "\n"
        }
      ]
    },
    {
      "uuid": "9978e398-1991-4e56-9261-a8eb42b2fa7e",
      "includes": [
        "media",
        "annotations",
        "label",
        "description"
      ],
      "start": 259,
      "end": 581,
      "file": "f3aead74-fbd4-40ad-be45-f5216d323a91",
      "type": "event",
      "children": [
        {
          "text": ""
        }
      ]
    },
    {
      "type": "paragraph",
      "children": [
        {
          "text": "The MacNeil/Lehrer Report; \"What to Do with the Failures in Public Housing: Fix Them Up, or Tear 'Em Down?\" | NewsHour Productions| April 3, 1978 "
        },
        {
          "text": "This video clip and associated transcript appear from 4:19 - 9:41 in the full record.",
          "italic": true
        },
        {
          "text": "\n\n"
        }
      ]
    }
  ],
  "created_at": "2026-06-02T13:18:45.921Z",
  "created_by": "benleff84",
  "title": "6. Crisis in Urban Housing Projects (1978)",
  "slug": "6-crisis-in-urban-housing-projects-1978",
  "updated_at": "2026-06-02T19:32:03.353Z",
  "updated_by": "benleff84",
  "autogenerate": {
    "enabled": false,
    "type": "event",
    "type_id": "9978e398-1991-4e56-9261-a8eb42b2fa7e"
  }
}